{
  "generated_at": "2026-07-20T12:15:36.909941+00:00",
  "source": "forecast_error_log.jsonl",
  "field": "cm",
  "windows": {
    "A_recent_15d": [
      "2026-07-04T00:00",
      "2026-07-19T00:00"
    ],
    "B_prior_15d": [
      "2026-06-19T00:00",
      "2026-07-04T00:00"
    ]
  },
  "fit_rules": {
    "fc_cc_threshold_pct": 80.0,
    "min_n_cell": 100,
    "min_improvement_pct": 3.0,
    "clip_range": [
      0,
      100
    ],
    "cross_fit_halves_stability_required": true
  },
  "cells": {
    "calm": {
      "0-5": {
        "n_a": 107,
        "n_b": 763,
        "delta_a": -7.009,
        "delta_b": -11.738,
        "improvement_ab_pct": 5.76,
        "improvement_ba_pct": 12.94,
        "delta_avg": -9.374,
        "verdict": "SHIP"
      },
      "12-23": {
        "n_a": 209,
        "n_b": 856,
        "delta_a": -1.665,
        "delta_b": -25.994,
        "improvement_ab_pct": 2.07,
        "improvement_ba_pct": -2.72,
        "delta_avg": -13.83,
        "verdict": "SKIP"
      },
      "24-47": {
        "n_a": 743,
        "n_b": 3030,
        "delta_a": -31.39,
        "delta_b": -27.995,
        "improvement_ab_pct": 33.35,
        "improvement_ba_pct": 31.94,
        "delta_avg": -29.693,
        "verdict": "SHIP"
      }
    },
    "frontal": {
      "12-23": {
        "n_a": 159,
        "n_b": 241,
        "delta_a": -25.453,
        "delta_b": -40.618,
        "improvement_ab_pct": 23.76,
        "improvement_ba_pct": 49.1,
        "delta_avg": -33.036,
        "verdict": "SHIP"
      },
      "24-47": {
        "n_a": 228,
        "n_b": 230,
        "delta_a": -36.557,
        "delta_b": -26.135,
        "improvement_ab_pct": 36.61,
        "improvement_ba_pct": 31.79,
        "delta_avg": -31.346,
        "verdict": "SHIP"
      }
    },
    "ne_flow": {
      "0-5": {
        "n_a": 352,
        "n_b": 255,
        "delta_a": -27.5,
        "delta_b": -28.161,
        "improvement_ab_pct": 16.46,
        "improvement_ba_pct": 26.38,
        "delta_avg": -27.83,
        "verdict": "SHIP"
      },
      "6-11": {
        "n_a": 582,
        "n_b": 426,
        "delta_a": -35.338,
        "delta_b": -33.815,
        "improvement_ab_pct": 29.14,
        "improvement_ba_pct": 30.03,
        "delta_avg": -34.577,
        "verdict": "SHIP"
      },
      "12-23": {
        "n_a": 1716,
        "n_b": 938,
        "delta_a": -43.441,
        "delta_b": -21.434,
        "improvement_ab_pct": 26.59,
        "improvement_ba_pct": 26.5,
        "delta_avg": -32.438,
        "verdict": "SHIP"
      },
      "24-47": {
        "n_a": 4331,
        "n_b": 2087,
        "delta_a": -44.2,
        "delta_b": -1.136,
        "improvement_ab_pct": -9.87,
        "improvement_ba_pct": 1.48,
        "delta_avg": -22.668,
        "verdict": "SKIP"
      }
    },
    "nw_flow": {
      "0-5": {
        "n_a": 1017,
        "n_b": 431,
        "delta_a": -24.821,
        "delta_b": -50.835,
        "improvement_ab_pct": 26.57,
        "improvement_ba_pct": 31.95,
        "delta_avg": -37.828,
        "verdict": "SHIP"
      },
      "6-11": {
        "n_a": 1118,
        "n_b": 532,
        "delta_a": -23.636,
        "delta_b": -43.88,
        "improvement_ab_pct": 24.33,
        "improvement_ba_pct": 30.83,
        "delta_avg": -33.758,
        "verdict": "SHIP"
      },
      "12-23": {
        "n_a": 1892,
        "n_b": 1351,
        "delta_a": -16.626,
        "delta_b": -54.754,
        "improvement_ab_pct": 18.03,
        "improvement_ba_pct": 37.5,
        "delta_avg": -35.69,
        "verdict": "SHIP"
      },
      "24-47": {
        "n_a": 3062,
        "n_b": 3065,
        "delta_a": -33.848,
        "delta_b": -36.173,
        "improvement_ab_pct": 31.39,
        "improvement_ba_pct": 38.98,
        "delta_avg": -35.01,
        "verdict": "SHIP"
      }
    },
    "pre_frontal": {
      "0-5": {
        "n_a": 529,
        "n_b": 507,
        "delta_a": -44.461,
        "delta_b": -30.722,
        "improvement_ab_pct": 34.67,
        "improvement_ba_pct": 35.33,
        "delta_avg": -37.592,
        "verdict": "SHIP"
      },
      "6-11": {
        "n_a": 963,
        "n_b": 839,
        "delta_a": -36.619,
        "delta_b": -32.403,
        "improvement_ab_pct": 28.08,
        "improvement_ba_pct": 30.37,
        "delta_avg": -34.511,
        "verdict": "SHIP"
      },
      "12-23": {
        "n_a": 1858,
        "n_b": 1509,
        "delta_a": -44.269,
        "delta_b": -37.12,
        "improvement_ab_pct": 37.37,
        "improvement_ba_pct": 37.21,
        "delta_avg": -40.694,
        "verdict": "SHIP"
      },
      "24-47": {
        "n_a": 3420,
        "n_b": 2092,
        "delta_a": -22.029,
        "delta_b": -19.101,
        "improvement_ab_pct": 19.66,
        "improvement_ba_pct": 20.67,
        "delta_avg": -20.565,
        "verdict": "SHIP"
      }
    },
    "se_flow": {
      "0-5": {
        "n_a": 591,
        "n_b": 889,
        "delta_a": -34.775,
        "delta_b": -22.56,
        "improvement_ab_pct": 12.48,
        "improvement_ba_pct": 27.78,
        "delta_avg": -28.668,
        "verdict": "SHIP"
      },
      "6-11": {
        "n_a": 1029,
        "n_b": 1680,
        "delta_a": -40.019,
        "delta_b": -23.244,
        "improvement_ab_pct": 25.92,
        "improvement_ba_pct": 29.5,
        "delta_avg": -31.632,
        "verdict": "SHIP"
      },
      "12-23": {
        "n_a": 2501,
        "n_b": 4564,
        "delta_a": -35.882,
        "delta_b": -19.921,
        "improvement_ab_pct": 22.18,
        "improvement_ba_pct": 26.72,
        "delta_avg": -27.901,
        "verdict": "SHIP"
      },
      "24-47": {
        "n_a": 4833,
        "n_b": 8724,
        "delta_a": -37.577,
        "delta_b": -36.048,
        "improvement_ab_pct": 29.09,
        "improvement_ba_pct": 42.23,
        "delta_avg": -36.812,
        "verdict": "SHIP"
      }
    },
    "sea_breeze": {
      "0-5": {
        "n_a": 200,
        "n_b": 273,
        "delta_a": -41.41,
        "delta_b": -13.473,
        "improvement_ab_pct": 19.4,
        "improvement_ba_pct": 19.2,
        "delta_avg": -27.441,
        "verdict": "SHIP"
      },
      "6-11": {
        "n_a": 235,
        "n_b": 259,
        "delta_a": -42.843,
        "delta_b": -18.564,
        "improvement_ab_pct": 31.05,
        "improvement_ba_pct": 25.15,
        "delta_avg": -30.703,
        "verdict": "SHIP"
      },
      "12-23": {
        "n_a": 292,
        "n_b": 453,
        "delta_a": -14.719,
        "delta_b": -8.753,
        "improvement_ab_pct": 16.88,
        "improvement_ba_pct": 7.87,
        "delta_avg": -11.736,
        "verdict": "SHIP"
      },
      "24-47": {
        "n_a": 854,
        "n_b": 1278,
        "delta_a": -2.234,
        "delta_b": -18.358,
        "improvement_ab_pct": 1.46,
        "improvement_ba_pct": 13.5,
        "delta_avg": -10.296,
        "verdict": "MARGIN"
      }
    },
    "sw_flow": {
      "0-5": {
        "n_a": 521,
        "n_b": 855,
        "delta_a": -35.637,
        "delta_b": -26.989,
        "improvement_ab_pct": 32.99,
        "improvement_ba_pct": 27.92,
        "delta_avg": -31.313,
        "verdict": "SHIP"
      },
      "6-11": {
        "n_a": 959,
        "n_b": 1218,
        "delta_a": -21.614,
        "delta_b": -15.223,
        "improvement_ab_pct": 21.87,
        "improvement_ba_pct": 13.6,
        "delta_avg": -18.419,
        "verdict": "SHIP"
      },
      "12-23": {
        "n_a": 2254,
        "n_b": 2444,
        "delta_a": -17.877,
        "delta_b": -21.689,
        "improvement_ab_pct": 17.47,
        "improvement_ba_pct": 17.46,
        "delta_avg": -19.783,
        "verdict": "SHIP"
      },
      "24-47": {
        "n_a": 5878,
        "n_b": 6502,
        "delta_a": -20.24,
        "delta_b": -15.692,
        "improvement_ab_pct": 16.84,
        "improvement_ba_pct": 15.21,
        "delta_avg": -17.966,
        "verdict": "SHIP"
      }
    },
    "unknown": {
      "6-11": {
        "n_a": 187,
        "n_b": 145,
        "delta_a": -34.209,
        "delta_b": -21.966,
        "improvement_ab_pct": 19.89,
        "improvement_ba_pct": 23.26,
        "delta_avg": -28.087,
        "verdict": "SHIP"
      },
      "12-23": {
        "n_a": 401,
        "n_b": 420,
        "delta_a": -22.04,
        "delta_b": -15.655,
        "improvement_ab_pct": 15.28,
        "improvement_ba_pct": 19.27,
        "delta_avg": -18.847,
        "verdict": "SHIP"
      },
      "24-47": {
        "n_a": 647,
        "n_b": 491,
        "delta_a": -29.946,
        "delta_b": -10.654,
        "improvement_ab_pct": 10.04,
        "improvement_ba_pct": 24.54,
        "delta_avg": -20.3,
        "verdict": "SHIP"
      }
    }
  },
  "rollup": {
    "ship": 29,
    "margin": 1,
    "skip": 2
  },
  "notes": "Stage 1 preview. Not wired to production. \u0394 is the mean signed bias (obs - fc) at fc_cc \u2265 threshold; correction adds \u0394 to the raw forecast when the fire condition holds. Fire condition at collector time: forecast cloud_cover for this lead \u2265 threshold AND cell (regime, band) is SHIP or MARGIN."
}